litechat/__init__.py
litechat/_codegpt/__init__.py
litechat/_codegpt/_codegpt_plugin_api.py
litechat/_codegpt/_legacy_codegpt_plugin.py
litechat/_codegpt/_prompts.py
litechat/_codegpt/example.py
litechat/_core/__init__.py
litechat/_core/_api.py
litechat/_core/_client.py
litechat/_core/_const.py
litechat/_core/_hf.py
litechat/_core/_oai.py
litechat/_core/_prompts.py
litechat/_core/_session.py
litechat/_core/_utils.py
litechat/_core/completions.py
litechat/_core/huggingchat_cookies.json
litechat/_llamacpp_oai_server.py
litechat/server.py
litechat/types/__init__.py
litechat/types/hf_models.py
litechat_server_run.py
litechat-0.0.69.dist-info/METADATA
litechat-0.0.69.dist-info/WHEEL
litechat-0.0.69.dist-info/entry_points.txt
litechat-0.0.69.dist-info/RECORD
