Metadata-Version: 2.1
Name: litechat
Version: 0.0.69
Summary: automated huggingchat openai style fastapi inference
Home-page: https://github.com/santhosh/
License: MIT
Author: Kammari Santhosh
Requires-Python: >=3.10,<4.0
Classifier: License :: OSI Approved :: MIT License
Classifier: Programming Language :: Python :: 3
Classifier: Programming Language :: Python :: 3.10
Classifier: Programming Language :: Python :: 3.11
Classifier: Programming Language :: Python :: 3.12
Classifier: Programming Language :: Python :: 3.13
Requires-Dist: ailitellm (>=0.1.10,<0.2.0)
Requires-Dist: playwright (>=1.49.1,<2.0.0)
Project-URL: Repository, https://github.com/santhosh/
